hyde/__init__.py
hyde/dwt3d.py
hyde/hyminor.py
hyde/hyres.py
hyde/otvca.py
hyde/utils.py
hyde/wsrrr.py
hyde/lowlevel/README.md
hyde/lowlevel/__init__.py
hyde/lowlevel/add_noise.py
hyde/lowlevel/dct.py
hyde/lowlevel/dwt3d.py
hyde/lowlevel/logging.py
hyde/lowlevel/utils.py
hyde/nn/ICVL_test.txt
hyde/nn/ICVL_train.txt
hyde/nn/README.md
hyde/nn/__init__.py
hyde/nn/call_nn_inference.py
hyde/nn/comm.py
hyde/nn/general_nn_utils.py
hyde/nn/helper.py
hyde/nn/hsi_denoising_complex.py
hyde/nn/hsi_denoising_gauss.py
hyde/nn/parsers.py
hyde/nn/requirements.txt
hyde/nn/training_utils.py
hyde/nn/datasets/__init__.py
hyde/nn/datasets/dataset_utils.py
hyde/nn/datasets/transforms.py
hyde/nn/models/__init__.py
hyde/nn/models/denet.py
hyde/nn/models/memnet.py
hyde/nn/models/qrnn/__init__.py
hyde/nn/models/qrnn/combinations.py
hyde/nn/models/qrnn/qrnn3d.py
hyde/nn/models/qrnn/redc3d.py
hyde/nn/models/qrnn/resnet.py
hyde/nn/qrnn3d/.gitignore
hyde/nn/qrnn3d/ICVL_test_complex.txt
hyde/nn/qrnn3d/README.md
hyde/nn/qrnn3d/__init__.py
hyde/spatial_domain/README.md
hyde/spatial_domain/__init__.py
hyde/spatial_domain/fast_hyde.py
hyde/spatial_domain/fast_hyin.py
hyde/spatial_domain/l1hymixde.py
hyde/transform_domain/README.md
hyde/transform_domain/__init__.py
hyde/transform_domain/forpdn.py
hyde/transform_domain/hyminor.py
hyde/transform_domain/hyres.py
hyde/transform_domain/otvca.py
hyde/transform_domain/wsrrr.py
hyde_images-0.4.3.dist-info/AUTHORS.md
hyde_images-0.4.3.dist-info/LICENSE.txt
hyde_images-0.4.3.dist-info/METADATA
hyde_images-0.4.3.dist-info/WHEEL
hyde_images-0.4.3.dist-info/top_level.txt
hyde_images-0.4.3.dist-info/RECORD
