Metadata-Version: 2.1
Name: hyde-images
Version: 0.4.3
Summary: Hyperspectral Denoising algorithm toolbox in Python for GPUs
Home-page: https://github.com/Helmholtz-AI-Energy/HyDe
Author: Helmholtz-AI-Energy
Author-email: consultant-helmholtz.ai@kit.edu
License: BSD-3-Clause
Project-URL: Source, https://github.com/Helmholtz-AI-Energy/HyDe
Project-URL: Changelog, https://github.com/Helmholtz-AI-Energy/HyDe/blob/main/CHANGELOG.md
Platform: any
Classifier: Development Status :: 4 - Beta
Classifier: License :: OSI Approved :: BSD License
Classifier: Programming Language :: Python
Classifier: Programming Language :: Python :: 3
Classifier: Programming Language :: Python :: 3.9
Classifier: Programming Language :: Python :: 3.8
Classifier: Programming Language :: Python :: 3.7
Classifier: Programming Language :: Python :: 3.6
Classifier: Intended Audience :: Science/Research
Classifier: Topic :: Scientific/Engineering
Requires-Python: >=3.6
License-File: LICENSE.txt
License-File: AUTHORS.md
Requires-Dist: numpy (>=1.13.0)
Requires-Dist: torch (>=1.8.0)
Requires-Dist: PyWavelets (>=1.1.1)
Requires-Dist: bm3d
Requires-Dist: kornia
Provides-Extra: testing
Requires-Dist: setuptools ; extra == 'testing'
Requires-Dist: pytest ; extra == 'testing'
Requires-Dist: pytest-cov ; extra == 'testing'
